bsm_calculator/__init__.py
bsm_calculator/model.py
bsm_calculator-0.1.0.dist-info/METADATA
bsm_calculator-0.1.0.dist-info/WHEEL
bsm_calculator-0.1.0.dist-info/top_level.txt
bsm_calculator-0.1.0.dist-info/RECORD
