Metadata-Version: 2.4
Name: bsm_calculator
Version: 0.1.0
Summary: High-performance Vectorized Black-Scholes-Merton Library
Author: Alok Kumar Yadav
Classifier: Programming Language :: Python :: 3
Classifier: Operating System :: OS Independent
Requires-Python: >=3.6
Requires-Dist: numpy
Requires-Dist: scipy
Dynamic: author
Dynamic: classifier
Dynamic: requires-dist
Dynamic: requires-python
Dynamic: summary
